<?xml version="1.0" encoding="utf-8"?>
<annotation>
   <folder>2</folder>
   <filename>1(445).jpg</filename>
   <path>F:\数据集图片\11956622\chuan\2\1(445).jpg</path>
   <source>
      <database>Unknown</database>
   </source>
   <size>
      <width>331</width>
      <height>220</height>
      <depth>3</depth>
   </size>
   <segmented>0</segmented>
   <object>
      <name>fanchuan</name>
      <pose>Unspecified</pose>
      <truncated>0</truncated>
      <difficult>0</difficult>
      <bndbox>
         <xmin>107</xmin>
         <ymin>15</ymin>
         <xmax>271</xmax>
         <ymax>127</ymax>
      </bndbox>
   </object>
</annotation>