<?xml version="1.0" encoding="utf-8"?>
<annotation>
   <folder>鸟</folder>
   <filename>bird(1220).jpg</filename>
   <path>F:\Yolo-V3\鸟\bird(1220).jpg</path>
   <source>
      <database>Unknown</database>
   </source>
   <size>
      <width>500</width>
      <height>480</height>
      <depth>3</depth>
   </size>
   <segmented>0</segmented>
   <object>
      <name>bird</name>
      <pose>Unspecified</pose>
      <truncated>0</truncated>
      <difficult>0</difficult>
      <bndbox>
         <xmin>119</xmin>
         <ymin>48</ymin>
         <xmax>387</xmax>
         <ymax>451</ymax>
      </bndbox>
   </object>
</annotation>