<?xml version="1.0" encoding="utf-8"?>
<annotation>
   <folder>船</folder>
   <filename>boat(1251).jpg</filename>
   <path>F:\Yolo-V3\船\boat(1251).JPG</path>
   <source>
      <database>Unknown</database>
   </source>
   <size>
      <width>550</width>
      <height>310</height>
      <depth>3</depth>
   </size>
   <segmented>0</segmented>
   <object>
      <name>youlun</name>
      <pose>Unspecified</pose>
      <truncated>0</truncated>
      <difficult>0</difficult>
      <bndbox>
         <xmin>33</xmin>
         <ymin>4</ymin>
         <xmax>473</xmax>
         <ymax>303</ymax>
      </bndbox>
   </object>
</annotation>