<?xml version="1.0" encoding="utf-8"?>
<annotation>
   <folder>船</folder>
   <filename>boat(65).jpg</filename>
   <path>F:\Yolo-V4数据集\船\boat(65).JPG</path>
   <source>
      <database>Unknown</database>
   </source>
   <size>
      <width>853</width>
      <height>1280</height>
      <depth>3</depth>
   </size>
   <segmented>0</segmented>
   <object>
      <name>fanchuan</name>
      <pose>Unspecified</pose>
      <truncated>0</truncated>
      <difficult>0</difficult>
      <bndbox>
         <xmin>155</xmin>
         <ymin>202</ymin>
         <xmax>683</xmax>
         <ymax>944</ymax>
      </bndbox>
   </object>
</annotation>