<?xml version="1.0" encoding="utf-8"?>
<annotation>
   <folder>船</folder>
   <filename>boat(983).jpg</filename>
   <path>F:\Yolo-V4数据集\船\boat(983).JPG</path>
   <source>
      <database>Unknown</database>
   </source>
   <size>
      <width>650</width>
      <height>419</height>
      <depth>3</depth>
   </size>
   <segmented>0</segmented>
   <object>
      <name>fanchuan</name>
      <pose>Unspecified</pose>
      <truncated>0</truncated>
      <difficult>0</difficult>
      <bndbox>
         <xmin>255</xmin>
         <ymin>30</ymin>
         <xmax>459</xmax>
         <ymax>269</ymax>
      </bndbox>
   </object>
</annotation>