<annotation>
	<folder>JPEGImages</folder>
	<filename>Cargoship(148).jpg</filename>
	<path>F:\VOC2007\VOC2007\JPEGImages\Cargoship(148).jpg</path>
	<source>
		<database>Unknown</database>
	</source>
	<size>
		<width>262</width>
		<height>159</height>
		<depth>3</depth>
	</size>
	<segmented>0</segmented>
	<object>
		<name>Cargoship</name>
		<pose>Unspecified</pose>
		<truncated>0</truncated>
		<difficult>0</difficult>
		<bndbox>
			<xmin>4</xmin>
			<ymin>14</ymin>
			<xmax>258</xmax>
			<ymax>151</ymax>
		</bndbox>
	</object>
</annotation>
