<?xml version="1.0" encoding="utf-8"?>
<annotation>
   <folder>鱼摆摆</folder>
   <filename>fish(326).jpg</filename>
   <path>F:\Yolo-V3\鱼摆摆\fish(326).jpg</path>
   <source>
      <database>Unknown</database>
   </source>
   <size>
      <width>719</width>
      <height>1080</height>
      <depth>3</depth>
   </size>
   <segmented>0</segmented>
   <object>
      <name>fish</name>
      <pose>Unspecified</pose>
      <truncated>0</truncated>
      <difficult>0</difficult>
      <bndbox>
         <xmin>24</xmin>
         <ymin>151</ymin>
         <xmax>372</xmax>
         <ymax>588</ymax>
      </bndbox>
   </object>
   <object>
      <name>fish</name>
      <pose>Unspecified</pose>
      <truncated>0</truncated>
      <difficult>0</difficult>
      <bndbox>
         <xmin>179</xmin>
         <ymin>328</ymin>
         <xmax>598</xmax>
         <ymax>736</ymax>
      </bndbox>
   </object>
   <object>
      <name>fish</name>
      <pose>Unspecified</pose>
      <truncated>1</truncated>
      <difficult>0</difficult>
      <bndbox>
         <xmin>1</xmin>
         <ymin>535</ymin>
         <xmax>535</xmax>
         <ymax>1009</ymax>
      </bndbox>
   </object>
</annotation>