<?xml version="1.0" encoding="utf-8"?>
<annotation>
   <folder>鱼摆摆</folder>
   <filename>fish(1394).jpg</filename>
   <path>F:\Yolo-V3\鱼摆摆\fish(1394).jpg</path>
   <source>
      <database>Unknown</database>
   </source>
   <size>
      <width>690</width>
      <height>431</height>
      <depth>3</depth>
   </size>
   <segmented>0</segmented>
   <object>
      <name>fish</name>
      <pose>Unspecified</pose>
      <truncated>0</truncated>
      <difficult>0</difficult>
      <bndbox>
         <xmin>103</xmin>
         <ymin>27</ymin>
         <xmax>471</xmax>
         <ymax>111</ymax>
      </bndbox>
   </object>
</annotation>