<?xml version="1.0" encoding="utf-8"?>
<annotation>
   <folder>鱼摆摆</folder>
   <filename>fish(629).jpg</filename>
   <path>F:\Yolo-V3\鱼摆摆\fish(629).jpg</path>
   <source>
      <database>Unknown</database>
   </source>
   <size>
      <width>1920</width>
      <height>1080</height>
      <depth>3</depth>
   </size>
   <segmented>0</segmented>
   <object>
      <name>fish</name>
      <pose>Unspecified</pose>
      <truncated>0</truncated>
      <difficult>0</difficult>
      <bndbox>
         <xmin>849</xmin>
         <ymin>159</ymin>
         <xmax>1416</xmax>
         <ymax>470</ymax>
      </bndbox>
   </object>
   <object>
      <name>fish</name>
      <pose>Unspecified</pose>
      <truncated>0</truncated>
      <difficult>0</difficult>
      <bndbox>
         <xmin>488</xmin>
         <ymin>537</ymin>
         <xmax>1407</xmax>
         <ymax>809</ymax>
      </bndbox>
   </object>
   <object>
      <name>fish</name>
      <pose>Unspecified</pose>
      <truncated>0</truncated>
      <difficult>0</difficult>
      <bndbox>
         <xmin>903</xmin>
         <ymin>621</ymin>
         <xmax>1606</xmax>
         <ymax>1034</ymax>
      </bndbox>
   </object>
</annotation>