<annotation>
	<folder>JPEGImages</folder>
	<filename>huolun(521).jpg</filename>
	<path>F:\VOC2007\VOC2007\JPEGImages\huolun(521).jpg</path>
	<source>
		<database>Unknown</database>
	</source>
	<size>
		<width>533</width>
		<height>300</height>
		<depth>3</depth>
	</size>
	<segmented>0</segmented>
	<object>
		<name>Cargoship</name>
		<pose>Unspecified</pose>
		<truncated>0</truncated>
		<difficult>0</difficult>
		<bndbox>
			<xmin>25</xmin>
			<ymin>11</ymin>
			<xmax>497</xmax>
			<ymax>253</ymax>
		</bndbox>
	</object>
	<object>
		<name>otherboat</name>
		<pose>Unspecified</pose>
		<truncated>0</truncated>
		<difficult>0</difficult>
		<bndbox>
			<xmin>269</xmin>
			<ymin>208</ymin>
			<xmax>384</xmax>
			<ymax>272</ymax>
		</bndbox>
	</object>
</annotation>
