<annotation>
	<folder>JPEGImages</folder>
	<filename>huolun(123).jpg</filename>
	<path>F:\VOC2007\VOC2007\JPEGImages\huolun(123).jpg</path>
	<source>
		<database>Unknown</database>
	</source>
	<size>
		<width>517</width>
		<height>300</height>
		<depth>3</depth>
	</size>
	<segmented>0</segmented>
	<object>
		<name>Cargoship</name>
		<pose>Unspecified</pose>
		<truncated>1</truncated>
		<difficult>0</difficult>
		<bndbox>
			<xmin>1</xmin>
			<ymin>164</ymin>
			<xmax>121</xmax>
			<ymax>202</ymax>
		</bndbox>
	</object>
	<object>
		<name>Cargoship</name>
		<pose>Unspecified</pose>
		<truncated>0</truncated>
		<difficult>0</difficult>
		<bndbox>
			<xmin>138</xmin>
			<ymin>39</ymin>
			<xmax>476</xmax>
			<ymax>261</ymax>
		</bndbox>
	</object>
</annotation>
