<annotation>
	<folder>JPG</folder>
	<filename>m(1164).jpg</filename>
	<path>F:\JPG\m(1164).jpg</path>
	<source>
		<database>Unknown</database>
	</source>
	<size>
		<width>650</width>
		<height>354</height>
		<depth>3</depth>
	</size>
	<segmented>0</segmented>
	<object>
		<name>Cargoship</name>
		<pose>Unspecified</pose>
		<truncated>0</truncated>
		<difficult>0</difficult>
		<bndbox>
			<xmin>94</xmin>
			<ymin>157</ymin>
			<xmax>608</xmax>
			<ymax>320</ymax>
		</bndbox>
	</object>
</annotation>
