<?xml version="1.0" encoding="utf-8"?>
<annotation>
   <folder>person</folder>
   <filename>person(1216).jpg</filename>
   <path>F:\Yolo-V3\person\person(1216).jpg</path>
   <source>
      <database>Unknown</database>
   </source>
   <size>
      <width>640</width>
      <height>424</height>
      <depth>3</depth>
   </size>
   <segmented>0</segmented>
   <object>
      <name>person</name>
      <pose>Unspecified</pose>
      <truncated>1</truncated>
      <difficult>0</difficult>
      <bndbox>
         <xmin>218</xmin>
         <ymin>101</ymin>
         <xmax>388</xmax>
         <ymax>424</ymax>
      </bndbox>
   </object>
</annotation>