<?xml version="1.0" encoding="utf-8"?>
<annotation>
   <folder>飞机405</folder>
   <filename>plane(293).jpg</filename>
   <path>F:\数据集图片\3e90d91f\飞机405\plane(293).jpg</path>
   <source>
      <database>Unknown</database>
   </source>
   <size>
      <width>400</width>
      <height>251</height>
      <depth>3</depth>
   </size>
   <segmented>0</segmented>
   <object>
      <name>person</name>
      <pose>Unspecified</pose>
      <truncated>0</truncated>
      <difficult>0</difficult>
      <bndbox>
         <xmin>40</xmin>
         <ymin>174</ymin>
         <xmax>57</xmax>
         <ymax>218</ymax>
      </bndbox>
   </object>
   <object>
      <name>person</name>
      <pose>Unspecified</pose>
      <truncated>0</truncated>
      <difficult>0</difficult>
      <bndbox>
         <xmin>65</xmin>
         <ymin>175</ymin>
         <xmax>81</xmax>
         <ymax>218</ymax>
      </bndbox>
   </object>
   <object>
      <name>person</name>
      <pose>Unspecified</pose>
      <truncated>0</truncated>
      <difficult>0</difficult>
      <bndbox>
         <xmin>85</xmin>
         <ymin>174</ymin>
         <xmax>108</xmax>
         <ymax>219</ymax>
      </bndbox>
   </object>
   <object>
      <name>person</name>
      <pose>Unspecified</pose>
      <truncated>0</truncated>
      <difficult>0</difficult>
      <bndbox>
         <xmin>110</xmin>
         <ymin>174</ymin>
         <xmax>129</xmax>
         <ymax>219</ymax>
      </bndbox>
   </object>
   <object>
      <name>person</name>
      <pose>Unspecified</pose>
      <truncated>0</truncated>
      <difficult>0</difficult>
      <bndbox>
         <xmin>151</xmin>
         <ymin>174</ymin>
         <xmax>173</xmax>
         <ymax>218</ymax>
      </bndbox>
   </object>
</annotation>