<annotation>
	<folder>JPG</folder>
	<filename>w(616).jpg</filename>
	<path>F:\JPG\w(616).jpg</path>
	<source>
		<database>Unknown</database>
	</source>
	<size>
		<width>1024</width>
		<height>819</height>
		<depth>1</depth>
	</size>
	<segmented>0</segmented>
	<object>
		<name>warship</name>
		<pose>Unspecified</pose>
		<truncated>0</truncated>
		<difficult>0</difficult>
		<bndbox>
			<xmin>54</xmin>
			<ymin>281</ymin>
			<xmax>906</xmax>
			<ymax>670</ymax>
		</bndbox>
	</object>
</annotation>
