<annotation>
	<folder>JPG</folder>
	<filename>y(143).jpg</filename>
	<path>F:\JPG\y(143).jpg</path>
	<source>
		<database>Unknown</database>
	</source>
	<size>
		<width>3500</width>
		<height>2625</height>
		<depth>3</depth>
	</size>
	<segmented>0</segmented>
	<object>
		<name>yacht</name>
		<pose>Unspecified</pose>
		<truncated>0</truncated>
		<difficult>0</difficult>
		<bndbox>
			<xmin>838</xmin>
			<ymin>828</ymin>
			<xmax>2872</xmax>
			<ymax>2142</ymax>
		</bndbox>
	</object>
</annotation>
