<?xml version="1.0" encoding="utf-8"?>
<annotation>
   <folder>游艇</folder>
   <filename>yacht(95).jpg</filename>
   <path>F:\Yolo-V3\游艇\yacht(95).jpg</path>
   <source>
      <database>Unknown</database>
   </source>
   <size>
      <width>250</width>
      <height>188</height>
      <depth>3</depth>
   </size>
   <segmented>0</segmented>
   <object>
      <name>yacht</name>
      <pose>Unspecified</pose>
      <truncated>0</truncated>
      <difficult>0</difficult>
      <bndbox>
         <xmin>9</xmin>
         <ymin>33</ymin>
         <xmax>237</xmax>
         <ymax>140</ymax>
      </bndbox>
   </object>
</annotation>